pycegm/__init__.py
pycegm/coords.py
pycegm/display.py
pycegm/mogi.py
pycegm/mproj.py
pycegm/pycegm.py
pycegm/units.py
pycegm/data/E451_20000818_20020719.unw
pycegm-0.1.dist-info/LICENSE
pycegm-0.1.dist-info/METADATA
pycegm-0.1.dist-info/WHEEL
pycegm-0.1.dist-info/top_level.txt
pycegm-0.1.dist-info/RECORD
