Metadata-Version: 2.1
Name: pycegm
Version: 0.1
Summary: Python CEGM contains all functions for CEG1705, CEG2707 and CEG3707 modules @ NCL
Home-page: https://github.com/koulali/pycegm
Author: achraf koulali
Author-email: achraf.koulali@ncl.ac.uk
License: MIT license
Keywords: pycegm
Classifier: Development Status :: 2 - Pre-Alpha
Classifier: Intended Audience :: Developers
Classifier: License :: OSI Approved :: MIT License
Classifier: Natural Language :: English
Classifier: Programming Language :: Python :: 3
Classifier: Programming Language :: Python :: 3.7
Classifier: Programming Language :: Python :: 3.8
Classifier: Programming Language :: Python :: 3.9
Classifier: Programming Language :: Python :: 3.10
Requires-Python: >=3.7
License-File: LICENSE
